Metadata-Version: 2.1
Name: jk-temporary
Version: 0.2021.12.6
Summary: Collection of utility functions and classes to manage temporary data.
Home-page: UNKNOWN
Author: Jürgen Knauth
Author-email: pubsrc@binary-overflow.de
License: Apache2
Keywords: temp,tempfiles,temporary
Platform: UNKNOWN
Classifier: Development Status :: 5 - Production/Stable
Classifier: License :: OSI Approved :: Apache Software License
Classifier: Programming Language :: Python :: 3
